README
arc2warc.py
setup.py
warc2warc.py
warcdump.py
warcextract.py
warcfilter.py
warcindex.py
warcvalid.py
hanzo/httptools/__init__.py
hanzo/httptools/messaging.py
hanzo/httptools/proxy.py
hanzo/httptools/semantics.py
hanzo/warctools/__init__.py
hanzo/warctools/arc.py
hanzo/warctools/archive_detect.py
hanzo/warctools/log.py
hanzo/warctools/record.py
hanzo/warctools/stream.py
hanzo/warctools/warc.py
hanzo_warc_tools.egg-info/PKG-INFO
hanzo_warc_tools.egg-info/SOURCES.txt
hanzo_warc_tools.egg-info/dependency_links.txt
hanzo_warc_tools.egg-info/top_level.txt