Metadata-Version: 1.0
Name: hanzo-warc-tools
Version: 0.2
Summary: Command line tools and libraries for handling and manipulating WARC files (and HTTP contents)
Home-page: UNKNOWN
Author: Thomas Figg
Author-email: thomas.figg@hanzoarchives.com
License: MIT License
Platform: UNKNOWN
